dycomutils/__init__.py
dycomutils/automation/__init__.py
dycomutils/automation/keystrokes.py
dycomutils/concurrancy/__init__.py
dycomutils/config/__init__.py
dycomutils/config/dict_to_config.py
dycomutils/grouping/__init__.py
dycomutils/serialization/__init__.py
dycomutils-0.2.0.dist-info/METADATA
dycomutils-0.2.0.dist-info/WHEEL
dycomutils-0.2.0.dist-info/top_level.txt
dycomutils-0.2.0.dist-info/RECORD
