Metadata-Version: 2.4
Name: dycomutils
Version: 0.2.0
Summary: CodeBase of important Functions
Author: Devin De Silva
Author-email: desild@rpi.edu
Keywords: python,codebase
Classifier: Development Status :: 3 - Alpha
Classifier: Intended Audience :: Developers
Classifier: Programming Language :: Python :: 3.9
Classifier: Operating System :: MacOS :: MacOS X
Classifier: Operating System :: Microsoft :: Windows
Requires-Dist: jsonlines
Dynamic: author
Dynamic: author-email
Dynamic: classifier
Dynamic: description
Dynamic: keywords
Dynamic: requires-dist
Dynamic: summary
